.gitignore
CMakeLists.txt
COPYING
INSTALL
README
data_import.py
distribute_setup.py
generate.py
scenario_model.py
server.py
setup.py
virtualenv.py
Mumoro.egg-info/PKG-INFO
Mumoro.egg-info/SOURCES.txt
Mumoro.egg-info/dependency_links.txt
Mumoro.egg-info/entry_points.txt
Mumoro.egg-info/requires.txt
Mumoro.egg-info/top_level.txt
ch/Makefile
ch/bench.cc
ch/contraction.cc
ch/contraction.h
ch/dijkstra.cc
ch/dijkstra.h
ch/graph.h
ch/main.cc
ch/martins.h
ch/query.cc
ch/query.h
ch/test.cc
lib/__init__.py
lib/bikestations.py
lib/datastructures.py
lib/elevation.py
lib/gtfs_reader.py
lib/kalkati_reader.py
lib/layer.py
lib/read.py
lib/statsbikes.py
lib/core/__init__.py
lib/core/graph_wrapper.cpp
lib/core/graph_wrapper.h
lib/core/martins.cpp
lib/core/martins.h
lib/core/martins_impl.h
lib/core/mumoro.i
lib/core/mumoro.py
lib/core/tsaggouris.cpp
lib/core/tsaggouris.h
scenarios/helsinki.py
scenarios/rennes_velo.py
scenarios/san_francisco.py
test/testunit.py
test/unittestimports.py
web/README.CONFIG.txt
web/__init__.py
web/shorturl.py
web/static/design.css
web/static/img/arrow-finish.png
web/static/img/arrow-green.png
web/static/img/arrow.png
web/static/img/asc.png
web/static/img/bg.png
web/static/img/bike.station.green.png
web/static/img/bike.station.orange.png
web/static/img/bike.station.red.png
web/static/img/by-nc-sa.png
web/static/img/by-sa.png
web/static/img/context-arrow-finish.png
web/static/img/context-arrow-green.png
web/static/img/desc.png
web/static/img/flag.eng.gif
web/static/img/flag.fr.gif
web/static/img/region.png
web/static/scripts/cloudmade.js
web/static/scripts/jquery-1.4.2.min.js
web/static/scripts/jquery.contextMenu.js
web/static/scripts/jquery.tablesorter.js
web/static/scripts/mumoro.js
web/templates/index.html
web/templates/info.html