Metadata-Version: 1.0
Name: Mumoro
Version: 0.0.2
Summary: Multimodal and multiobjective routing
Home-page: http://github.com/Tristramg/mumoro/
Author: Tristram Graebener
Author-email: tristramg@gmail.com
License: GPLv3
Platform: UNKNOWN
